AUTHORS.rst
CONTRIBUTING.rst
HISTORY.rst
LICENSE
MANIFEST.in
README.rst
setup.py
doconv/__init__.py
doconv/doconv.py
doconv/exceptions.py
doconv/log.py
doconv/util.py
doconv.egg-info/PKG-INFO
doconv.egg-info/SOURCES.txt
doconv.egg-info/dependency_links.txt
doconv.egg-info/entry_points.txt
doconv.egg-info/not-zip-safe
doconv.egg-info/requires.txt
doconv.egg-info/top_level.txt
doconv/plugin/__init__.py
doconv/plugin/asciidoc.py
doconv/plugin/asciidoctor.py
doconv/plugin/base.py
doconv/plugin/docbooktodita.py
doconv/plugin/docbooktodita/db2dita/dbReader.xsl
doconv/plugin/docbooktodita/db2dita/docbook2dita.xsl
doconv/plugin/docbooktodita/ditaWriter/conceptOutput.xsl
doconv/plugin/docbooktodita/ditaWriter/ditabaseOutput.xsl
doconv/plugin/docbooktodita/ditaWriter/highlightDomainOutput.xsl
doconv/plugin/docbooktodita/ditaWriter/metaDeclOutput.xsl
doconv/plugin/docbooktodita/ditaWriter/programmingDomainOutput.xsl
doconv/plugin/docbooktodita/ditaWriter/referenceOutput.xsl
doconv/plugin/docbooktodita/ditaWriter/softwareDomainOutput.xsl
doconv/plugin/docbooktodita/ditaWriter/taskOutput.xsl
doconv/plugin/docbooktodita/ditaWriter/tblDeclOutput.xsl
doconv/plugin/docbooktodita/ditaWriter/topicOutput.xsl
doconv/plugin/docbooktodita/ditaWriter/uiDomainOutput.xsl
doconv/plugin/docbooktodita/ditaWriter/utilitiesDomainOutput.xsl
docs/authors.rst
docs/contributing.rst
docs/creating_a_plugin.rst
docs/doconv.plugin.rst
docs/doconv.rst
docs/features.rst
docs/history.rst
docs/index.rst
docs/installation.rst
docs/introduction.rst
docs/modules.rst
docs/plugins.rst
docs/readme.rst
docs/usage.rst