Metadata-Version: 1.1
Name: doconv
Version: 0.1.5
Summary: conversion from AsciiDoc and DocBook to DITA
Home-page: https://github.com/jmourelos/doconv
Author: Jacob Mourelos
Author-email: jacob.mourelos@gmail.com
License: BSD
Keywords: doconv
Platform: UNKNOWN
Classifier: Development Status :: 2 - Pre-Alpha
Classifier: Intended Audience :: Developers
Classifier: License :: OSI Approved :: BSD License
Classifier: Natural Language :: English
Classifier: Programming Language :: Python :: 2
Classifier: Programming Language :: Python :: 2.6
Classifier: Programming Language :: Python :: 2.7
Classifier: Programming Language :: Python :: 3
Classifier: Programming Language :: Python :: 3.3
Classifier: Programming Language :: Python :: 3.4
Classifier: Programming Language :: Python :: 3.5
